insighttrail/__init__.py
insighttrail/logger.py
insighttrail/metrics.py
insighttrail/middleware.py
insighttrail/traces.py
insighttrail/templates/index.html
insighttrail-0.1.0.dist-info/LICENSE
insighttrail-0.1.0.dist-info/METADATA
insighttrail-0.1.0.dist-info/WHEEL
insighttrail-0.1.0.dist-info/top_level.txt
insighttrail-0.1.0.dist-info/RECORD
