Metadata-Version: 2.1
Name: insighttrail
Version: 0.1.0
Summary: An observability middleware for Flask with a real-time analytics UI.
Home-page: https://github.com/insightTrail/insighttrail
Author: Team InsightTrail
Author-email: teaminsighttrail@gmail.com
Classifier: Development Status :: 4 - Beta
Classifier: Framework :: Flask
Classifier: Intended Audience :: Developers
Classifier: Topic :: System :: Logging
Classifier: Topic :: System :: Monitoring
Classifier: License :: OSI Approved :: MIT License
Classifier: Programming Language :: Python :: 3
Classifier: Programming Language :: Python :: 3.7
Classifier: Programming Language :: Python :: 3.8
Classifier: Programming Language :: Python :: 3.9
Classifier: Programming Language :: Python :: 3.10
Classifier: Operating System :: OS Independent
Requires-Python: >=3.7
License-File: LICENSE
Requires-Dist: Flask>=2.0
Requires-Dist: psutil
Requires-Dist: requests
